<annotation>
	<folder>cropped_lps</folder>
	<filename>311.jpg</filename>
	<path>/Users/eo/Documents/Programming/LPReader/archive/cropped_lps/cropped_lps/311.jpg</path>
	<source>
		<database>Unknown</database>
	</source>
	<size>
		<width>99</width>
		<height>49</height>
		<depth>3</depth>
	</size>
	<segmented>0</segmented>
	<object>
		<name>license</name>
		<pose>Unspecified</pose>
		<truncated>0</truncated>
		<difficult>0</difficult>
		<bndbox>
			<xmin>3</xmin>
			<ymin>3</ymin>
			<xmax>97</xmax>
			<ymax>44</ymax>
		</bndbox>
	</object>
</annotation>
